howcode
