Metadata-Version: 1.1
Name: howcode
Version: 0.1.2
Summary: Instant Cross Platform coding answers via the command line
Home-page: https://github.com/zevtyardt
Author: Val (zvtyrdt.id)
Author-email: alviandtm@gmail.com
License: MIT
Keywords: howdoi help console command line answer termux
Platform: UNKNOWN
Classifier: Development Status :: 5 - Production/Stable
Classifier: Environment :: Console
Classifier: Intended Audience :: Developers
Classifier: Programming Language :: Python :: 2.7
Classifier: Programming Language :: Python :: 3
Classifier: Programming Language :: Python :: 3.3
Classifier: Programming Language :: Python :: 3.4
Classifier: Programming Language :: Python :: 3.5
Classifier: Programming Language :: Python :: 3.6
Classifier: Topic :: Documentation
